OneNeuron_PYPI/Perceptron.py
OneNeuron_PYPI/__init__.py
OneNeuron_PYPI_gopichandu_tech-0.0.2.dist-info/LICENSE
OneNeuron_PYPI_gopichandu_tech-0.0.2.dist-info/METADATA
OneNeuron_PYPI_gopichandu_tech-0.0.2.dist-info/WHEEL
OneNeuron_PYPI_gopichandu_tech-0.0.2.dist-info/top_level.txt
OneNeuron_PYPI_gopichandu_tech-0.0.2.dist-info/RECORD
