Metadata-Version: 2.1
Name: OneNeuron-PYPI-gopichandu-tech
Version: 0.0.2
Summary: A small example package
Home-page: https://github.com/gopichandu-tech/OneNeuron_PYPI
Author: Example Author
Author-email: author@example.com
License: UNKNOWN
Project-URL: Bug Tracker, https://github.com/gopichandu-tech/OneNeuron_PYPI/issues
Platform: UNKNOWN
Classifier: Programming Language :: Python :: 3
Classifier: License :: OSI Approved :: MIT License
Classifier: Operating System :: OS Independent
Requires-Python: >=3.7
License-File: LICENSE
Requires-Dist: numpy
Requires-Dist: tqdm
